sphere_base/__init__.py
sphere_base/calc.py
sphere_base/clipboard.py
sphere_base/config.py
sphere_base/constants.py
sphere_base/history.py
sphere_base/serializable.py
sphere_base/sphere_main_menu.py
sphere_base/sphere_main_window.py
sphere_base/utils.py
sphere_base/edge/__init__.py
sphere_base/edge/edge_drag.py
sphere_base/edge/graphic_edge.py
sphere_base/edge/graphic_line.py
sphere_base/edge/inter_sphere_edge.py
sphere_base/edge/surface_edge.py
sphere_base/model/__init__.py
sphere_base/model/mesh.py
sphere_base/model/model.py
sphere_base/model/models.py
sphere_base/model/obj_file_loader.py
sphere_base/model/resources/__init__.py
sphere_base/model/resources/icons/__init__.py
sphere_base/model/resources/meshes/__init__.py
sphere_base/model/resources/meshes/crosshair.mtl
sphere_base/model/resources/meshes/crosshair.obj
sphere_base/model/resources/meshes/cubesphere.mtl
sphere_base/model/resources/meshes/cubesphere.obj
sphere_base/model/resources/meshes/line_1x1.mtl
sphere_base/model/resources/meshes/line_1x1.obj
sphere_base/model/resources/meshes/node_disc1.mtl
sphere_base/model/resources/meshes/node_disc1.obj
sphere_base/model/resources/meshes/skybox.mtl
sphere_base/model/resources/meshes/skybox.obj
sphere_base/model/resources/meshes/sphere1.mtl
sphere_base/model/resources/meshes/sphere1.obj
sphere_base/model/resources/meshes/sphere_small.mtl
sphere_base/model/resources/meshes/sphere_small.obj
sphere_base/model/resources/meshes/square1x1.mtl
sphere_base/model/resources/meshes/square1x1.obj
sphere_base/model/resources/meshes/vertex1.mtl
sphere_base/model/resources/meshes/vertex1.obj
sphere_base/model/resources/shaders/__init__.py
sphere_base/model/resources/shaders/frag_2d.glsl
sphere_base/model/resources/shaders/frag_circle.glsl
sphere_base/model/resources/shaders/frag_default.glsl
sphere_base/model/resources/shaders/frag_holo.glsl
sphere_base/model/resources/shaders/frag_holo_sphere.glsl
sphere_base/model/resources/shaders/frag_node.glsl
sphere_base-0.1.25.dist-info/LICENSE
sphere_base-0.1.25.dist-info/METADATA
sphere_base-0.1.25.dist-info/WHEEL
sphere_base-0.1.25.dist-info/top_level.txt
sphere_base-0.1.25.dist-info/RECORD
